npmscanner/__init__.py
npmscanner/__main__.py
npmscanner/banner.py
npmscanner/core/__init__.py
npmscanner/core/scanner.py
npmscanner/core/patterns/__init__.py
npmscanner/core/patterns/metadata.py
npmscanner/core/patterns/npm_specific.py
npmscanner/core/patterns/source_code.py
npmscanner/core/patterns/unified_analyzer.py
npmscanner/reports/__init__.py
npmscanner/reports/html_generator.py
npmscanner/utils/__init__.py
npmscanner/utils/colors.py
npmscanner/utils/config.py
npmscanner-0.1.2.dist-info/licenses/LICENSE
npmscanner-0.1.2.dist-info/METADATA
npmscanner-0.1.2.dist-info/WHEEL
npmscanner-0.1.2.dist-info/entry_points.txt
npmscanner-0.1.2.dist-info/top_level.txt
npmscanner-0.1.2.dist-info/RECORD
