Metadata-Version: 2.4
Name: npmscanner
Version: 0.1.2
Summary: Advanced NPM Security Scanner for supply chain analysis
Home-page: https://crimson7.io
Author: Crimson7 Security
Author-email: security@crimson7.io
Project-URL: Bug Reports, https://github.com/crimson7/npmscanner/issues
Project-URL: Source, https://github.com/crimson7/npmscanner
Project-URL: Documentation, https://crimson7.io/docs
Project-URL: Homepage, https://crimson7.io
Keywords: security,npm,supply-chain,vulnerability,malware,obfuscation
Classifier: Development Status :: 5 - Production/Stable
Classifier: Intended Audience :: Developers
Classifier: Intended Audience :: System Administrators
Classifier: Topic :: Security
Classifier: Topic :: Software Development :: Quality Assurance
Classifier: License :: OSI Approved :: MIT License
Classifier: Programming Language :: Python :: 3
Classifier: Programming Language :: Python :: 3.7
Classifier: Programming Language :: Python :: 3.8
Classifier: Programming Language :: Python :: 3.9
Classifier: Programming Language :: Python :: 3.10
Classifier: Programming Language :: Python :: 3.11
Classifier: Operating System :: OS Independent
Requires-Python: >=3.7
License-File: LICENSE
Requires-Dist: requests>=2.28.0
Requires-Dist: urllib3>=1.26.0
Dynamic: author
Dynamic: author-email
Dynamic: classifier
Dynamic: description
Dynamic: description-content-type
Dynamic: home-page
Dynamic: keywords
Dynamic: license-file
Dynamic: project-url
Dynamic: requires-dist
Dynamic: requires-python
Dynamic: summary
